{
	"id": "6694676",
	"name": "사골국 끓이는 법",
	"thumbnail": "https://recipe1.ezmember.co.kr/cache/recipe/2015/05/16/2976da0bb55fa4f352b4f3a1d244ae7e1.JPG",
	"url": "https://www.10000recipe.com/recipe/6694676",
	"ingredient_ids": [
		995
	],
	"time": "2이상",
	"ingre_list": [
		{
			"ingre_name": "사골",
			"ingre_count": "",
			"ingre_unit": ""
		},
		{
			"ingre_name": "물",
			"ingre_count": "",
			"ingre_unit": ""
		}
	],
	"recipe": [
		"1. 사골을 3시간 정도 참물에 넣고 핏물을 빼주세요.",
		"2. 핏 물을 뺀 사골을 잘 씻어서 뼈가 잠길 정도로 물을 넣고 한번 팔팔 끓여주세요. 그럼 사진 같이 검게 핏물이 변하면서 뼈에 남아있던 핏물이 빠져요.",
		"3. 핏물을 버리고 찬물에 2~3번 씻어서 깨끗한 물을 붓고 끓이기 시작합니다. 처음에 약불로 끓이다가 끓기 시작하면 약한불로 끓이세요.",
		"4. 요렇게 밤새 끓인 첫번째 사골 국물이예요. 물 양은 뼈에 1.5~2배 정도 넣으심 되요. 아직은 뽀얀 사골국 빛이 아니네요. 서늘한 곳에서 식혀주세요.",
		"5. 서늘한 곳에 두면 기름이 굳어져요. 그 기름을 걷어내서 버리고 용기에 담아두세요. 이런 방법으로 3~4번 사골국물을 낸 다음 같이 섞을 꺼예요.",
		"6. 요게 두번째 사골국물. 기름 굳이지 전이랑 기름기가 많아요. 약간 기름기진 한데 맛은 더 고소하고 국물도 잘 우러나네요.  3번째건 사진이 없네요. 밤낮없이 사골국만 끓여더니 빨리 헤치우고 싶은 마음에...전 3번 끓여서 같이 섞어서식힌 다음 팩마다 먹을 만큼씩 담아 냉동실에 보관했어요."
	],
	"recipe_img": [
		"https://recipe1.ezmember.co.kr/cache/recipe/2015/05/16/77f0781123e16e5d2adf8aeaea02574b1.JPG",
		"https://recipe1.ezmember.co.kr/cache/recipe/2015/05/16/a66375f71dd3bf82a5ba54655edc7ef71.JPG",
		"https://recipe1.ezmember.co.kr/cache/recipe/2015/05/16/d49f6dfb4c5e02a0acb62aaba6c6372a1.JPG",
		"https://recipe1.ezmember.co.kr/cache/recipe/2015/05/16/54a1b2a82f075fcae050c49cb649c2c31.JPG",
		"https://recipe1.ezmember.co.kr/cache/recipe/2015/05/16/2f1a60f2fb5f622d061926015936f3971.jpg",
		"https://recipe1.ezmember.co.kr/cache/recipe/2015/05/16/7fa5639fa065130eae2dbf152fbc23f41.JPG"
	]
}