{
	"id": "6833498",
	"name": "얼갈이김치담그는법, 새콤하게 익혀 먹으면 더 맛있는 얼갈이배추김치 ",
	"thumbnail": "https://recipe1.ezmember.co.kr/cache/recipe/2015/09/04/a419219cef006affd2bbe774c10cd7e41.jpg",
	"url": "https://www.10000recipe.com/recipe/6833498",
	"ingredient_ids": [
		595,
		757,
		540,
		667,
		224,
		333,
		287,
		226,
		233,
		28
	],
	"time": "90",
	"ingre_list": [
		{
			"ingre_name": "얼갈이배추",
			"ingre_count": "2",
			"ingre_unit": "단"
		},
		{
			"ingre_name": "쪽파",
			"ingre_count": "2",
			"ingre_unit": "줌"
		},
		{
			"ingre_name": "홍고추",
			"ingre_count": "5",
			"ingre_unit": "개"
		},
		{
			"ingre_name": "꽃소금",
			"ingre_count": "1",
			"ingre_unit": "컵정도"
		},
		{
			"ingre_name": "찹쌀가루",
			"ingre_count": "1/2",
			"ingre_unit": "컵"
		},
		{
			"ingre_name": "고춧가루",
			"ingre_count": "13",
			"ingre_unit": "큰술"
		},
		{
			"ingre_name": "멸치액젓",
			"ingre_count": "5",
			"ingre_unit": "큰술"
		},
		{
			"ingre_name": "까나리액젓",
			"ingre_count": "5",
			"ingre_unit": "큰술"
		},
		{
			"ingre_name": "설탕",
			"ingre_count": "2",
			"ingre_unit": "작은술"
		},
		{
			"ingre_name": "다진마늘",
			"ingre_count": "3",
			"ingre_unit": "큰술"
		},
		{
			"ingre_name": "생강",
			"ingre_count": "2",
			"ingre_unit": "큰술"
		}
	],
	"recipe": [
		"1. 얼갈이배추 2단을 다듬은 다음 소금물을 만들어 붓고 위에 꽃소금을 조금씩 뿌려 1시간 정도 절여 줍니다",
		"2. 찹쌀가루 반컵에 물 2컵을 넣고 잘 섞고 저으며 끓여서  완전히 식힌 다음 고춧가루 13, 멸치액젓5, 까나리액젓5,  설탕2, 다진마늘3, 생강2를 넣어 양념장을 만드세요",
		"3. 절여진 얼갈이 배추는 3~4번 정도  깨끗한 물에 씻어서 물기를 쫘악~ 빼주세요",
		"4. 홍고추 5개는 물을 조금 넣고 믹서기에 곱게 갈아 주세요",
		"5. 볼에 물기 뺀 얼갈이 담고, 쪽파 2줌과 양념장, 홍고추 갈아 놓은걸 한꺼번에 붓고",
		"6. 양념이 잘 묻도록 살 살 버무리면 됩니다~ 마지막에 맛을 봐서 싱거우면 소금으로 간하고 통깨도 듬뿍 넣어 주세요"
	],
	"recipe_img": [
		"https://recipe1.ezmember.co.kr/cache/recipe/2015/09/04/e37c052bc281801beb8cb2bfae9975bf1.jpg",
		"https://recipe1.ezmember.co.kr/cache/recipe/2015/09/04/7409323b0fb45b93244a8e51c12e386b1.jpg",
		"https://recipe1.ezmember.co.kr/cache/recipe/2015/09/04/9713a71b53a917ae63cf26bdf81e82aa1.jpg",
		"https://recipe1.ezmember.co.kr/cache/recipe/2015/09/04/399c114679f97d6ae991a4a8ea173dee1.jpg",
		"https://recipe1.ezmember.co.kr/cache/recipe/2015/09/04/8d19576e51dc4429c3dee6f9fb4b1cf81.jpg",
		"https://recipe1.ezmember.co.kr/cache/recipe/2015/09/04/29acb989e62a6022bb0883a0afbbccc11.jpg"
	]
}