{
	"id": "6879726",
	"name": "노량진 수산시장에서 구입한 동태알과 고니로 알탕 끓이는 법",
	"thumbnail": "https://recipe1.ezmember.co.kr/cache/recipe/2017/11/17/88ed08e504abbf1ada948e857f091ee41.jpg",
	"url": "https://www.10000recipe.com/recipe/6879726",
	"ingredient_ids": [
		19,
		47,
		3,
		29
	],
	"time": "15",
	"ingre_list": [
		{
			"ingre_name": "무",
			"ingre_count": "1/4",
			"ingre_unit": "개"
		},
		{
			"ingre_name": "고니",
			"ingre_count": "100",
			"ingre_unit": "g"
		},
		{
			"ingre_name": "동태알",
			"ingre_count": "100",
			"ingre_unit": "g"
		},
		{
			"ingre_name": "고추가루",
			"ingre_count": "1",
			"ingre_unit": "스푼"
		},
		{
			"ingre_name": "집간장",
			"ingre_count": "1",
			"ingre_unit": "스푼"
		},
		{
			"ingre_name": "콩나물",
			"ingre_count": "1",
			"ingre_unit": "줌"
		},
		{
			"ingre_name": "양파",
			"ingre_count": "1/2",
			"ingre_unit": "개"
		},
		{
			"ingre_name": "마늘",
			"ingre_count": "1",
			"ingre_unit": "스푼"
		}
	],
	"recipe": [
		"1. 노량진수산시장에서 구입해온 냉동된 고니는 한번 먹을 크기로 썰어",
		"2. 이렇게 소분하여 냉동실 보관",
		"3. 동태알도 마찬가지로 한번 먹을 분량씩  소분하여 냉동실 보관",
		"4. 이제 알탕 끓이는 법 시작해 볼게요 멸치와 다시마 새우등 넣고 끓여 냉동실 보관하는 만능육수 준비했고요",
		"5. 알탕의 시원한 맛을 더해줄 무도 준비",
		"6. 알탕 끓이는 법의 주재료인 고니와 알도 씻어 준비",
		"7. 무 넣고 끓인 육수에 알과 고니를 넣고 끓여줍니다",
		"8. 거기에 고춧가루 한 스푼과 집간장 한 스푼 넣고 다시 팔팔 끓여준 후",
		"9. 콩나물과 양파 넣고",
		"10. 마늘 한 스푼까지 추가하여",
		"11. 팔팔 끓여주기만 하면 준비 끝 며칠 전부터 마트 가서 파를 산다는 걸 계속 깜빡하네요",
		"12. 완성된 알탕끓이는 법 시식의 시간입니다 파도 없고 쑥갓도 없이 끓여 맛없으면 어쩌나 하고 먹어본 순간 ~~~ 맛있습니다  싱싱함 그 자체입니다 하나도 비리지 않습니다"
	],
	"recipe_img": [
		"https://recipe1.ezmember.co.kr/cache/recipe/2017/11/17/66a22a6d9945ee9487a0ea55b236e8451.jpg",
		"https://recipe1.ezmember.co.kr/cache/recipe/2017/11/17/3d5390caa433f3e049a9602878c17b6d1.jpg",
		"https://recipe1.ezmember.co.kr/cache/recipe/2017/11/17/fdf33b0e009f2a75d2d5e982584bbdb51.jpg",
		"https://recipe1.ezmember.co.kr/cache/recipe/2017/11/17/7debdd17b95186300a235a925e1ddfec1.jpg",
		"https://recipe1.ezmember.co.kr/cache/recipe/2017/11/17/da424591f6c448e6d5d9461dafb6c85f1.jpg",
		"https://recipe1.ezmember.co.kr/cache/recipe/2017/11/17/db5e2e6e9cde108a9ecd6335496d5e4d1.jpg",
		"https://recipe1.ezmember.co.kr/cache/recipe/2017/11/17/5b4795327819d6a714f338ac2117993e1.jpg",
		"https://recipe1.ezmember.co.kr/cache/recipe/2017/11/17/baaea81ba93f783d29a387a92fa3f7211.jpg",
		"https://recipe1.ezmember.co.kr/cache/recipe/2017/11/17/fd1361fd4bfe4fee780dfec68bdcd99c1.jpg",
		"https://recipe1.ezmember.co.kr/cache/recipe/2017/11/17/cd9368b9f73a9d2fb778f3ae297c0a131.jpg",
		"https://recipe1.ezmember.co.kr/cache/recipe/2017/11/17/26e7dd6d396661e60112bb878a8242021.jpg",
		"https://recipe1.ezmember.co.kr/cache/recipe/2017/11/17/a7ce091345bf1910737f9aa8eb6695821.jpg"
	]
}