{
	"id": "6940044",
	"name": "백종원 멸치볶음 만드는법 아이반찬으로 딱",
	"thumbnail": "https://recipe1.ezmember.co.kr/cache/recipe/2020/08/25/7ab3feea159ef13e0bf2f370fea0a79e1.jpg",
	"url": "https://www.10000recipe.com/recipe/6940044",
	"ingredient_ids": [
		677,
		341,
		226,
		660,
		543,
		504,
		29,
		840
	],
	"time": "10",
	"ingre_list": [
		{
			"ingre_name": "잔멸치",
			"ingre_count": "3",
			"ingre_unit": "컵"
		},
		{
			"ingre_name": "진간장",
			"ingre_count": "2",
			"ingre_unit": "숟갈"
		},
		{
			"ingre_name": "물엿",
			"ingre_count": "1",
			"ingre_unit": "숟갈"
		},
		{
			"ingre_name": "설탕",
			"ingre_count": "1",
			"ingre_unit": "숟갈"
		},
		{
			"ingre_name": "참기름",
			"ingre_count": "1",
			"ingre_unit": "숟갈"
		},
		{
			"ingre_name": "통깨",
			"ingre_count": "",
			"ingre_unit": "약간"
		},
		{
			"ingre_name": "식용유",
			"ingre_count": "2",
			"ingre_unit": "숟갈"
		},
		{
			"ingre_name": "마늘",
			"ingre_count": "",
			"ingre_unit": ""
		},
		{
			"ingre_name": "홍고추",
			"ingre_count": "",
			"ingre_unit": ""
		},
		{
			"ingre_name": "견과류",
			"ingre_count": "",
			"ingre_unit": ""
		}
	],
	"recipe": [
		"1. 1) 마늘, 홍고추를 얇게 썰어주세요. ",
		"2. 잔멸치 초벌로 볶아주기 팬에 멸치를 덖어주고 채에 바쳐서 부스러기를 털어주어요. 이렇게 한번 덖어주면 비린내도 없어지고~ 맛이 깔끔해지더라고요.                    ",
		"3. 팬에 식용유 2숟갈 넣고 마늘과 홍고추를 먼저 볶아요. 매콤한 마늘과 고추의 향이 올라오면서 맛이 더욱 풍부해져요. ",
		"4. 미리 볶아둔 멸치도 넣고 볶아주세요.                    ",
		"5. 간장 2숟갈, 물엿 1숟갈, 설탕 1숟갈을 준비해요. ",
		"6. 멸치를 팬 한켠으로 밀어두고~ 간장2숟갈, 물엿1숟갈, 설탕 1숟갈 넣고 바글바글 졸여주세요. 이렇게 간장을 한번 끓이면 불맛이 올라와서 더 맛있어요. ",
		"7. 양념장에 멸치를 같이 잘 섞어주세요. ",
		"8. 마지막으로 참기름 1숟갈~ 그리고 통깨 솔솔 적당히 뿌려주면 백종원 잔멸치볶음 완성! "
	],
	"recipe_img": [
		"https://recipe1.ezmember.co.kr/cache/recipe/2020/09/28/a8e80c9bfd9b4026a77a87a5076708051.jpg",
		"https://recipe1.ezmember.co.kr/cache/recipe/2020/09/28/4eb05a57bb718fe008270f642809e8961.jpg",
		"https://recipe1.ezmember.co.kr/cache/recipe/2020/09/28/d8b22f2ea19cfbc7b7f7ad8b33ca8cc31.jpg",
		"https://recipe1.ezmember.co.kr/cache/recipe/2020/09/28/b1f7e56e10c373eeb9fad9a487c91f7e1.jpg",
		"https://recipe1.ezmember.co.kr/cache/recipe/2020/09/28/e2189c15d094c4c54e271bf67fd7850a1.jpg",
		"https://recipe1.ezmember.co.kr/cache/recipe/2020/09/28/e291580f5962765a9fae7e975cce2d491.jpg",
		"https://recipe1.ezmember.co.kr/cache/recipe/2020/09/28/2d38157858d7a35255c2946ea9fde5b41.jpg"
	]
}