{
	"id": "6940408",
	"name": "집에서 양갈비 스테이크 만드는 법!",
	"thumbnail": "https://recipe1.ezmember.co.kr/cache/recipe/2020/08/29/0462c6e8941ba255a171991f8f9d57261.jpg",
	"url": "https://www.10000recipe.com/recipe/6940408",
	"ingredient_ids": [
		3,
		27,
		29,
		22
	],
	"time": "30",
	"ingre_list": [
		{
			"ingre_name": "숄더랙",
			"ingre_count": "500",
			"ingre_unit": "g"
		},
		{
			"ingre_name": "양파",
			"ingre_count": "1/2",
			"ingre_unit": "개"
		},
		{
			"ingre_name": "대파",
			"ingre_count": "1",
			"ingre_unit": "개"
		},
		{
			"ingre_name": "양송이",
			"ingre_count": "3",
			"ingre_unit": "개"
		},
		{
			"ingre_name": "마늘",
			"ingre_count": "4",
			"ingre_unit": "알"
		},
		{
			"ingre_name": "피망",
			"ingre_count": "1",
			"ingre_unit": "개"
		},
		{
			"ingre_name": "베이비야채",
			"ingre_count": "",
			"ingre_unit": ""
		}
	],
	"recipe": [
		"1. 파프리카를 먹기 좋은 크기로 썰어줍니다",
		"2. 양파는 반개를 4등분 해주시구요",
		"3. 마늘도 반 갈라서 준비 해주세요",
		"4. 양송이는 4등분 해주시구요",
		"5. 대파는 2~3센티 간격으로 잘라주세요",
		"6. 양고기는 핏기좀 제거 해주세요",
		"7. 예열된 팬에다가 앞뒤로 30초씩!! 뒤집어 주면서 구워주세요! 저는 총 6번 뒤집었어요!",
		"8. 구워진 고기는 레스팅좀 해주신뒤",
		"9. 레스팅 되는동안 야채를 볶아주시는데 쌘불에서 후추와 소금을 넣고 볶아주세요",
		"10. 플레이팅 하시고 드시면 됩니다 저는 베이비 야채까지 사용해서 그위에 발사믹 소스 살짝 뿌려주었어요~",
		"11. 와사비랑도 궁합이 좋아요! 양고기에 마지막으로 소금 후추간을 해주셔도 좋구요~"
	],
	"recipe_img": [
		"https://recipe1.ezmember.co.kr/cache/recipe/2020/08/29/423cfb5bedc92dad23cdf4904b3ddc7f1.jpg",
		"https://recipe1.ezmember.co.kr/cache/recipe/2020/08/29/9b2e6ef3d0efad86313c9805cf4c0cf71.jpg",
		"https://recipe1.ezmember.co.kr/cache/recipe/2020/08/29/f4ee2898597be287b781a9bf087810491.jpg",
		"https://recipe1.ezmember.co.kr/cache/recipe/2020/08/29/bd5054cba26ffdc11d182bee8f3d85631.jpg",
		"https://recipe1.ezmember.co.kr/cache/recipe/2020/08/29/5bb3e6ca368d0a46d43564742eb9cff21.jpg",
		"https://recipe1.ezmember.co.kr/cache/recipe/2020/08/29/02a8dd2cb44bb6fef785e87bc0328e971.jpg",
		"https://recipe1.ezmember.co.kr/cache/recipe/2020/08/29/abe4e6981b638d58e73230972a02c4771.jpg",
		"https://recipe1.ezmember.co.kr/cache/recipe/2020/08/29/a3dfd297b11f4e19547c8be31e9c9bbe1.jpg",
		"https://recipe1.ezmember.co.kr/cache/recipe/2020/08/29/2543453fd51797aaee91c4600677b6871.jpg",
		"https://recipe1.ezmember.co.kr/cache/recipe/2020/08/29/65f93ef888e76ca8585224e1b2aa5ff61.jpg",
		"https://recipe1.ezmember.co.kr/cache/recipe/2020/08/29/4c39d131ca4f7f6f4715616dae7504d61.jpg"
	]
}