{
	"id": "6940637",
	"name": "쪽파전 : 시장에서 파는 맛이랑 똑같은 담백고소한 쪽파전",
	"thumbnail": "https://recipe1.ezmember.co.kr/cache/recipe/2020/09/02/24a6b106f2db0b91b80d142c4b8ceaa21.png",
	"url": "https://www.10000recipe.com/recipe/6940637",
	"ingredient_ids": [
		295,
		387,
		995,
		504,
		497
	],
	"time": "15",
	"ingre_list": [
		{
			"ingre_name": "쪽파또는실파잡았을때100원크기정도",
			"ingre_count": "100",
			"ingre_unit": "원 크기 정도"
		},
		{
			"ingre_name": "해물모듬",
			"ingre_count": "1/2",
			"ingre_unit": "팩"
		},
		{
			"ingre_name": "청양고추",
			"ingre_count": "1",
			"ingre_unit": "개"
		},
		{
			"ingre_name": "계란",
			"ingre_count": "1",
			"ingre_unit": "개"
		},
		{
			"ingre_name": "부침가루",
			"ingre_count": "200",
			"ingre_unit": "ml"
		},
		{
			"ingre_name": "물",
			"ingre_count": "160",
			"ingre_unit": "ml"
		},
		{
			"ingre_name": "식용유",
			"ingre_count": "",
			"ingre_unit": "적당히"
		},
		{
			"ingre_name": "소금",
			"ingre_count": "",
			"ingre_unit": ""
		},
		{
			"ingre_name": "후추",
			"ingre_count": "1",
			"ingre_unit": "꼬집"
		}
	],
	"recipe": [
		"1. 1) 재료를 준비해주세요. 쪽파 또는 실파는 프라이팬 크기에 맞춰서 잘라주시고, 청양고추는 씹을때 맵지 않도록 얇게 썰어주세요. 사진을 준비하지 못했지만 해물 모듬은 넣기 전에 한번 흐르는 물에 씻어서 준비해주세요 !쪽파 또는 실파 잡았을 때 100원 크기 정도, 청양고추 1개, 해물 모듬 1/2팩",
		"2. 2) 반죽물을 만들어주세요. 섞은 후 들면 흐를 정도로 묽게 만들어주세요 : ) 간은 소금, 후추 한 꼬집 넣어주세요.부침가루 200ml, 물 160ml, 소금, 후추 한 꼬집묽어야지 나중에 재료들 안으로 잘 스며들어 자리를 잡을 수 있어요 !",
		"3. 3) 전을 만들어 마무리 해주세요. 식용유를 적당히 프라이팬에 둘러, 불을 조절 하며 쪽파를 넣고 그 위에 해물을 얹은 후, 국자로 반죽물을 그 위에 살살 부어주세요. 그러고 난 후, 계란을 풀어 위에 얹어주시고 마지막으로는 청양고추 얹고 뒤집고 하다 보면 바로 쪽파전 완성이예요 : )중불저는 뒤집는 걸 되게 못해서 이상하게 됐지만, 반죽물을 골고루 부어주셔서 재료가 뭉치게끔 해주시면 될 것 같아요 !"
	],
	"recipe_img": [
		"https://recipe1.ezmember.co.kr/cache/recipe/2020/09/02/85f01e01d79c54deddc29810cd4f38191.jpg",
		"https://recipe1.ezmember.co.kr/cache/recipe/2020/09/02/02f9254b6ac3adbd55346f9fccb3081d1.jpg",
		"https://recipe1.ezmember.co.kr/cache/recipe/2020/09/02/c96b4280b322e5ea3478393d0a335a281.jpg"
	]
}