{
	"id": "6940870",
	"name": "#오징어요리 #오징어볶음만들기 #돼지불고기와오징어볶음의만남 #돼지불고기와 오징어볶음, 그리고 바게트빵!!!",
	"thumbnail": "https://recipe1.ezmember.co.kr/cache/recipe/2020/09/04/9f097903ddc5c232fe1694ccad1a15371.jpg",
	"url": "https://www.10000recipe.com/recipe/6940870",
	"ingredient_ids": [
		65,
		7,
		3,
		473,
		224,
		233,
		27,
		457,
		292,
		843,
		547,
		1018,
		333,
		843,
		292,
		233,
		457
	],
	"time": "30",
	"ingre_list": [
		{
			"ingre_name": "오징어",
			"ingre_count": "3",
			"ingre_unit": "마리"
		},
		{
			"ingre_name": "애호박",
			"ingre_count": "1/2",
			"ingre_unit": "개"
		},
		{
			"ingre_name": "냉동모둠채소",
			"ingre_count": "3",
			"ingre_unit": "컵"
		},
		{
			"ingre_name": "양파",
			"ingre_count": "1",
			"ingre_unit": "개"
		},
		{
			"ingre_name": "고추장",
			"ingre_count": "2",
			"ingre_unit": "큰술"
		},
		{
			"ingre_name": "고춧가루",
			"ingre_count": "2",
			"ingre_unit": "큰술"
		},
		{
			"ingre_name": "다진마늘",
			"ingre_count": "1",
			"ingre_unit": "큰술"
		},
		{
			"ingre_name": "대파",
			"ingre_count": "1",
			"ingre_unit": "대"
		},
		{
			"ingre_name": "다진생강",
			"ingre_count": "1",
			"ingre_unit": "작은술"
		},
		{
			"ingre_name": "맛술",
			"ingre_count": "1",
			"ingre_unit": "큰술"
		},
		{
			"ingre_name": "매실액",
			"ingre_count": "3",
			"ingre_unit": "큰술"
		},
		{
			"ingre_name": "양조간장",
			"ingre_count": "1",
			"ingre_unit": "큰술"
		},
		{
			"ingre_name": "갈치속젓",
			"ingre_count": "1",
			"ingre_unit": "큰술"
		},
		{
			"ingre_name": "천연조미료",
			"ingre_count": "1",
			"ingre_unit": "작은술"
		},
		{
			"ingre_name": "돼지불고기",
			"ingre_count": "200",
			"ingre_unit": "g"
		},
		{
			"ingre_name": "돼지불고기",
			"ingre_count": "200",
			"ingre_unit": "g"
		},
		{
			"ingre_name": "후추",
			"ingre_count": "1",
			"ingre_unit": "작은술"
		},
		{
			"ingre_name": "멸치액젓",
			"ingre_count": "2",
			"ingre_unit": "큰술"
		},
		{
			"ingre_name": "매실액",
			"ingre_count": "1",
			"ingre_unit": "큰술"
		},
		{
			"ingre_name": "맛술",
			"ingre_count": "1",
			"ingre_unit": "큰술"
		},
		{
			"ingre_name": "다진마늘",
			"ingre_count": "1",
			"ingre_unit": "작은술"
		},
		{
			"ingre_name": "다진생강",
			"ingre_count": "1",
			"ingre_unit": "꼬집"
		}
	],
	"recipe": [
		"1. 애호박을 사각형 모양으로 썰어서 준비합니다. 애호박 1/2으로 썰어 준 후에 그 토막을 다시금 세로로 반으로 썰어 줍니다. 그럼 다음에 편으로 썰어 주시면 이런 모양이 나옵니다.",
		"2. 냉동채소를 넣어 줍니다. 모둠채소라서 그냥 바로바로 사용하기 편하기도 하고 모둠이라서 당근도 있고 브로콜린도 있고 마도 있고요.",
		"3. 양파는 두껍게 채썰어서 넣어 주고 대파도 큼지막하게 썰어서 넣어 줍니다. 한 4cm정도로 썰어 주시면 되겠네요.",
		"4. 자 오징어도 역시 비슷한 두께와 길이로 썰어서 넣어 줍니다.",
		"5. 다진마늘, 다진생강, 천연조미료를 넣어 줍니다. 천연조미료가 없으시면 표고가루나 아니면 다시마가루, 새우가루를 활용하셔도 좋습니다. 그것도 없으시면 패스하셔도 됩니다.",
		"6. 고추장, 고춧가루, 갈치속젓, 양조간장, 매실액, 맛술을 넣어 줍니다.",
		"7. 조물조물 무쳐 줍니다. 그리고는 랩을 씌워서는 냉장고에 잠시 숙성시켜 줍니다.",
		"8. 숙성시킨 오징어불고기를 활활 타오르는 팬에 넣어서 볶아 줍니다.",
		"9. 그리고 한쪽에 돼지불고기를 넣어 줍니다. 돼지불고기 양념은 아주 간단하게 해 주었습니다. 멸치액젓, 매실액, 다진마늘, 다진생강, 맛술을 넣어서 조물조물 무쳐 준 후에 같이 넣어 줍니다. 불고기 양념 어렵지 않습니다. 물론 배를 갈고 키위도 갈고 사과도 갈고 하면 더욱 좋겠지만 간단하게 해서 먹기에는 이 방법이 제일 좋습니다.",
		"10. 완성접시에 바게트를 썰어서 올려 주고요. 이번에 청진식당의 오삼불고기의 맛은 바로 바게트가 마무리해주는 것입니다.",
		"11. 오징어볶음과 더불어서 초간단하게 양념한 돼지불고기까지 올려진 청진식당.........따라하기!!! 오징어볶음 완성입니다. 거기에 바게트까지. 밥에 비벼서 먹을 수도 있지만 굳이 밥이 아니어도 바게트빵에 올려서 먹으면 이탈리아음식 같지 않을까요. 아니면 스페인요리 ㅋㅋㅋ"
	],
	"recipe_img": [
		"https://recipe1.ezmember.co.kr/cache/recipe/2020/09/04/8391694f05f23c33df27fa5880fa9a2e1.jpg",
		"https://recipe1.ezmember.co.kr/cache/recipe/2020/09/04/e661bbe72443e4461ddf77d8562e22381.jpg",
		"https://recipe1.ezmember.co.kr/cache/recipe/2020/09/04/29b5ee69961f959ad8091e49db6c39871.jpg",
		"https://recipe1.ezmember.co.kr/cache/recipe/2020/09/04/3cd3f173815df3ef7a770c224cd574431.jpg",
		"https://recipe1.ezmember.co.kr/cache/recipe/2020/09/04/684e935954c4d3bcd12a703011bf12b51.jpg",
		"https://recipe1.ezmember.co.kr/cache/recipe/2020/09/04/48eb5e275c1bd4fb564bd8c0e5a65e201.jpg",
		"https://recipe1.ezmember.co.kr/cache/recipe/2020/09/04/95656c3696e6e809629f790f010646c01.jpg",
		"https://recipe1.ezmember.co.kr/cache/recipe/2020/09/04/6af496257d1a2e18096a1d28f2f1429b1.jpg",
		"https://recipe1.ezmember.co.kr/cache/recipe/2020/09/04/3e4846689a21b5d4d9b7371c8c56e81a1.jpg",
		"https://recipe1.ezmember.co.kr/cache/recipe/2020/09/04/c21f2b4872fd11e792b22030e7c0cf031.jpg",
		"https://recipe1.ezmember.co.kr/cache/recipe/2020/09/04/9796154b97160bd17bd8e1519aceca141.jpg"
	]
}