{
	"id": "6941752",
	"name": "건강하고 맛있는 피자 밥피자 만들기 밥피자 만드는법",
	"thumbnail": "https://recipe1.ezmember.co.kr/cache/recipe/2020/09/13/c06127d8548fd86486e31fe3bc36d91a1.jpg",
	"url": "https://www.10000recipe.com/recipe/6941752",
	"ingredient_ids": [
		3,
		628,
		732,
		198,
		212,
		702
	],
	"time": "15",
	"ingre_list": [
		{
			"ingre_name": "밥",
			"ingre_count": "1",
			"ingre_unit": "국그릇"
		},
		{
			"ingre_name": "양파",
			"ingre_count": "1/2",
			"ingre_unit": "개"
		},
		{
			"ingre_name": "빨간파프리카",
			"ingre_count": "1/2",
			"ingre_unit": "개"
		},
		{
			"ingre_name": "노란파프리카",
			"ingre_count": "1/2",
			"ingre_unit": "개"
		},
		{
			"ingre_name": "햄",
			"ingre_count": "1",
			"ingre_unit": "개"
		},
		{
			"ingre_name": "토마토소스",
			"ingre_count": "1",
			"ingre_unit": "컵"
		},
		{
			"ingre_name": "계란",
			"ingre_count": "1",
			"ingre_unit": "개"
		},
		{
			"ingre_name": "버터",
			"ingre_count": "1",
			"ingre_unit": "T"
		},
		{
			"ingre_name": "모짜렐라치즈",
			"ingre_count": "150",
			"ingre_unit": "g"
		},
		{
			"ingre_name": "파슬리",
			"ingre_count": "",
			"ingre_unit": "약간"
		}
	],
	"recipe": [
		"1. 햄과 양파, 빨간 파프리카, 노란 파프리카를 프라이팬에 볶아주세요강불",
		"2. 양파의 색이 투명 빛으로 변하기 시작하면 토마토소스를 넣고 볶아주세요",
		"3. 밥이 뭉쳐질 수 있도록 밥과 계란을 골고루 섞어주세요잘 안 뭉쳐지는 흩어지는 밥을 사용하시는 것은 추천해 드리지 않습니다",
		"4. 프라이팬에 버터를 녹여주세요 그리고 밥을 넓게 펼쳐 주신 다음에 3분 정도 구워주시고 뒤집어서 1분 정도 추가로 구워주세요버터를 녹일때 : 약불 -> 밥을 구워줄 때 : 중불 -> 밥을 뒤집어서 구워줄 때 : 약불",
		"5. 밥 위에 피자 소스를 펴 발라주시고 소스 위에 치즈를 올려주세요 그 다음에 뚜껑을 덮고 치즈가 녹을 때까지 구워주세요약불",
		"6. 완성된 밥피자는 예쁘게 플레이팅 해주시고 위에 파슬리를 뿌려 마무리해주세요"
	],
	"recipe_img": [
		"https://recipe1.ezmember.co.kr/cache/recipe/2020/09/13/a63d89956401d0516662df7b3ed71eca1.jpg",
		"https://recipe1.ezmember.co.kr/cache/recipe/2020/09/13/55404c7e8259cb6577b50496b8349f0f1.jpg",
		"https://recipe1.ezmember.co.kr/cache/recipe/2020/09/13/42b7fbf8b61ee90a37003d0798f40d5f1.jpg",
		"https://recipe1.ezmember.co.kr/cache/recipe/2020/09/13/d60c2f34d2798353ccb35d01287a48731.jpg",
		"https://recipe1.ezmember.co.kr/cache/recipe/2020/09/13/b496cd07b193079ee287311ce16a52741.jpg",
		"https://recipe1.ezmember.co.kr/cache/recipe/2020/09/13/04a8a79742e80080dda10a28d40249bb1.jpg"
	]
}