{
	"id": "6941488",
	"name": "꾸덕하고 진한 오트밀 토마토리조또 간단레시피",
	"thumbnail": "https://recipe1.ezmember.co.kr/cache/recipe/2020/09/10/0a54e2a8fbb02dc0b22e0718e09cc58a1.jpg",
	"url": "https://www.10000recipe.com/recipe/6941488",
	"ingredient_ids": [
		572,
		22,
		51,
		300,
		55,
		175,
		216,
		1006
	],
	"time": "10",
	"ingre_list": [
		{
			"ingre_name": "오트밀",
			"ingre_count": "5",
			"ingre_unit": "T"
		},
		{
			"ingre_name": "피망",
			"ingre_count": "1",
			"ingre_unit": "개"
		},
		{
			"ingre_name": "토마토",
			"ingre_count": "1",
			"ingre_unit": "개"
		},
		{
			"ingre_name": "닭가슴살",
			"ingre_count": "110",
			"ingre_unit": "g"
		},
		{
			"ingre_name": "팽이버섯",
			"ingre_count": "1",
			"ingre_unit": "개"
		},
		{
			"ingre_name": "올리브",
			"ingre_count": "3",
			"ingre_unit": "알"
		},
		{
			"ingre_name": "피자치즈",
			"ingre_count": "100",
			"ingre_unit": "g"
		},
		{
			"ingre_name": "우유",
			"ingre_count": "",
			"ingre_unit": "조금"
		},
		{
			"ingre_name": "하인즈노슈가케찹",
			"ingre_count": "2",
			"ingre_unit": "T"
		},
		{
			"ingre_name": "스리라차소스",
			"ingre_count": "2",
			"ingre_unit": "T"
		}
	],
	"recipe": [
		"1. 닭가슴살, 피망, 토마토, 팽이버섯을 다져주세요",
		"2. 올리브유를 두른 팬에 볶아주세요",
		"3. 후추를 넣어 3분 정도 더 볶아주세요",
		"4. 오트밀 5숟가락에 우유를 잠길 정도로 부어주세요",
		"5. 하인즈노슈가케찹 2숟가락 넣어 같이 섞어주세요",
		"6. 준비된 채소볶음을 듬뿍 올려주세요",
		"7. 올리브를 슬라이스로 잘라 위에 올려주세요",
		"8. 매콤핫 스리라차소스를 뿌려주세요",
		"9. 피자치즈 한봉지를 뜯어 골고루 올린 뒤 파슬리도 살짝 뿌려주세요",
		"10. 전자레인지에 2분 돌려주시면 완성!전자레인지"
	],
	"recipe_img": [
		"https://recipe1.ezmember.co.kr/cache/recipe/2020/09/10/00505c1ad66b8a6718ad52873d8261f51.jpg",
		"https://recipe1.ezmember.co.kr/cache/recipe/2020/09/10/2aee8e6883fe90eae2c08414020a97331.jpg",
		"https://recipe1.ezmember.co.kr/cache/recipe/2020/09/10/f0c14cad062022410dd09aee91ee6bdd1.jpg",
		"https://recipe1.ezmember.co.kr/cache/recipe/2020/09/10/603162d91d2929969de420b3a9833d4e1.jpg",
		"https://recipe1.ezmember.co.kr/cache/recipe/2020/09/10/f6bc70549e60a6669ad904dc6e4da8d91.jpg",
		"https://recipe1.ezmember.co.kr/cache/recipe/2020/09/10/01040cd26f47328da9cd03157211e3a11.jpg",
		"https://recipe1.ezmember.co.kr/cache/recipe/2020/09/10/b9bf86d5e7662394365370ac034d6fd61.jpg",
		"https://recipe1.ezmember.co.kr/cache/recipe/2020/09/10/a2bf31fae94c8000fdadfac9de8329181.jpg",
		"https://recipe1.ezmember.co.kr/cache/recipe/2020/09/10/30160aac2069b330711ee26c6457a4c21.jpg",
		"https://recipe1.ezmember.co.kr/cache/recipe/2020/09/10/04492acb132ec550727c23bb9e9a0fcf1.jpg"
	]
}