{
	"id": "6942532",
	"name": "(코로나극복)두부 장김치메밀국수: 채소가 고명이 아니라 국수가 되는 다이어트국수",
	"thumbnail": "https://recipe1.ezmember.co.kr/cache/recipe/2020/09/22/259ce783781deb32c9a224c95563e2941.jpg",
	"url": "https://www.10000recipe.com/recipe/6942532",
	"ingredient_ids": [
		8,
		21,
		1024,
		51,
		323,
		327,
		497,
		577
	],
	"time": "30",
	"ingre_list": [
		{
			"ingre_name": "메밀국수",
			"ingre_count": "50",
			"ingre_unit": "그램"
		},
		{
			"ingre_name": "오이",
			"ingre_count": "1/2",
			"ingre_unit": "개"
		},
		{
			"ingre_name": "양배추",
			"ingre_count": "4",
			"ingre_unit": "장내외"
		},
		{
			"ingre_name": "쌈채소",
			"ingre_count": "5",
			"ingre_unit": "장내외"
		},
		{
			"ingre_name": "토마토",
			"ingre_count": "1",
			"ingre_unit": "개"
		},
		{
			"ingre_name": "장김치",
			"ingre_count": "",
			"ingre_unit": "적당량"
		},
		{
			"ingre_name": "두부",
			"ingre_count": "1/3",
			"ingre_unit": "모"
		},
		{
			"ingre_name": "들기름",
			"ingre_count": "",
			"ingre_unit": ""
		},
		{
			"ingre_name": "소금",
			"ingre_count": "",
			"ingre_unit": ""
		},
		{
			"ingre_name": "후추",
			"ingre_count": "",
			"ingre_unit": ""
		},
		{
			"ingre_name": "장김치국물1컵+",
			"ingre_count": "2",
			"ingre_unit": "큰술"
		},
		{
			"ingre_name": "다시마물",
			"ingre_count": "2",
			"ingre_unit": "컵"
		},
		{
			"ingre_name": "얼음",
			"ingre_count": "",
			"ingre_unit": ""
		},
		{
			"ingre_name": "와사비",
			"ingre_count": "",
			"ingre_unit": ""
		}
	],
	"recipe": [
		"1. 생수에 다시마를 넣어 다시마물을 만든다.",
		"2. 장김치 담궈둔걸 꺼낸다.",
		"3. 장김치국물1 다시마물2를 섞어 국수국물을 만든다.미리 만들어 냉동실에서 살얼음 얼릴 정도로 두던가 냉장실에 차게 두었다 먹으면 좋아요",
		"4. 두부를 마른팬에 볶은 후 소금, 후추, 들기름넣어 양념한다 두부를 미리 물 뺀 후 볶으면 시간절약이 돼요.",
		"5. 채소면으로 쓸 채소는 길고 가늘게 채썰고 고명도 적당히 썰어둔다. 대표적인 채소면인 오이는 가능하면 꼭 넣어주시고 다른 채소는 냉장고 사정껏 넣어주세요.쌈채소를 가늘게 채썰어 주어도 좋아요",
		"6. 메밀면은 1인분량의 반만 넣어 소면과 같은 방법으로 삶아 찬물에 헹군 후 물기를 빼둔다.",
		"7. 그릇에 메밀면과 채소면을 담는다",
		"8. 준비해둔 국물과 얼음 담고 두부볶음과 생와사비를 얹는다"
	],
	"recipe_img": [
		"https://recipe1.ezmember.co.kr/cache/recipe/2020/09/22/026bfa0bbfe8bfbf83eb93745678ea411.jpg",
		"https://recipe1.ezmember.co.kr/cache/recipe/2020/09/22/33cdc037277b475123511bc8a0e059571.jpg",
		"https://recipe1.ezmember.co.kr/cache/recipe/2020/09/22/c95216f4e9e306f6ceacb17b281039c01.jpg",
		"https://recipe1.ezmember.co.kr/cache/recipe/2020/09/22/d7d4a44187eb92b9430b54c332ba13a01.jpg",
		"https://recipe1.ezmember.co.kr/cache/recipe/2020/09/22/683468861f8cbfef6001a2cf9c0a3e861.jpg",
		"https://recipe1.ezmember.co.kr/cache/recipe/2020/09/22/6cddefd43f90303109769dbf04544f8e1.jpg",
		"https://recipe1.ezmember.co.kr/cache/recipe/2020/09/22/b5914de26bd9cefdf7945690311466401.jpg",
		"https://recipe1.ezmember.co.kr/cache/recipe/2020/09/22/26cdae5a4d977c811307502a4cdfb0741.jpg"
	]
}