{
	"id": "6944023",
	"name": "과카몰리 만들기 : 아보카도 보관법",
	"thumbnail": "https://recipe1.ezmember.co.kr/cache/recipe/2020/10/13/d49c1782b96f0481d493311d2f0d20d11.jpg",
	"url": "https://www.10000recipe.com/recipe/6944023",
	"ingredient_ids": [
		162,
		3,
		51,
		233,
		497,
		225
	],
	"time": "20",
	"ingre_list": [
		{
			"ingre_name": "아보카도",
			"ingre_count": "4",
			"ingre_unit": "개"
		},
		{
			"ingre_name": "양파",
			"ingre_count": "1",
			"ingre_unit": "개"
		},
		{
			"ingre_name": "토마토",
			"ingre_count": "2",
			"ingre_unit": "개"
		},
		{
			"ingre_name": "다진마늘",
			"ingre_count": "1",
			"ingre_unit": "큰술"
		},
		{
			"ingre_name": "실란트로",
			"ingre_count": "1",
			"ingre_unit": "줌"
		},
		{
			"ingre_name": "매운고추",
			"ingre_count": "3",
			"ingre_unit": "개"
		},
		{
			"ingre_name": "소금",
			"ingre_count": "",
			"ingre_unit": ""
		},
		{
			"ingre_name": "후춧가루",
			"ingre_count": "",
			"ingre_unit": ""
		},
		{
			"ingre_name": "라임주스",
			"ingre_count": "2",
			"ingre_unit": "큰술"
		}
	],
	"recipe": [
		"1. 아보카도를 다량으로 구입 할 때는 잘 익은 보라색 부터 덜 익은 초록색까지 익은 단계별로 구입하면 좋습니다. 상온에 아보카도를 두고 껍질이 검은 보라색이 되면 제일 먹기 좋은 상태입니다. 덜익은 아보카도는 잘 으깨지지도 않고 약간 쓴맛이 납니다. 아보카도는 바나나 처럼 후숙과일이기 때문에 반드시 상온에서 껍질이 검보라색이 된 후에 냉장보관해야 합니다. 껍질이 초록색일 때 냉장고에 넣으면 그 상태에서 썩습니다. (처음에 멋 모르고 냉장고에 넣었다가 폭망~ 했던 흑역사가...)  ​  ​  ​",
		"2. 아보카도는 반으로 가르고 씨를 칼로 콕! 비틀어 틀면서 빼줍니다. ",
		"3. 잘 익은 아보카도는 숟가락으로 떠내면서 껍질과 과육을 분리합니다. ",
		"4. 잘 익은 아보카도 3개 ",
		"5. 토마토 양파 1개 실란트로 한줌 매운고추 3개 다진마늘 1큰술 ※소금은 입맛에 맞게 넣어줍니다.",
		"6. 후춧가루를 입맛에 맞게 넣고",
		"7. 라임주스 2큰술을 넣습니다. 재료들을 잘 섞어주면 맛있은 과카몰리 완성! Guacamole ",
		"8. 아보카도는 다지거나 으깨거나 원하는 식감에 따라 만들면 됩니다. 만든직 후 바로 먹어도 좋지만, 공기에 접촉되지 않도록 과카몰리위에 비닐랩을 씌운 후 냉장고에서 2시간 또는 하루 정도 숙성후에 먹으면 정말 맛이 좋습니다. ",
		"9. 바삭한 또띠아 칩에 과카몰리 듬뿍~ 올려 한입 고소한 칩에 부드럽고 고소한 아보카도맛과 매콤한 고추와 알싸한 마늘맛을 부드럽게 감싸주는 토마토의 맛 아삭 쌉싸름 양파 그리고 실라트로향과 시큼 라임향이 너무도 잘 어우러지며 맛 궁합이 차알~~~떡!!!!!"
	],
	"recipe_img": [
		"https://recipe1.ezmember.co.kr/cache/recipe/2020/10/13/ad66f81fe51b38c3d26578f9314fb1c81.jpg",
		"https://recipe1.ezmember.co.kr/cache/recipe/2020/10/13/cace1f474f23d9b11ba4a0068a312f891.jpg",
		"https://recipe1.ezmember.co.kr/cache/recipe/2020/10/13/e6d64b0e31a8ff5671ea40b77b548a981.jpg",
		"https://recipe1.ezmember.co.kr/cache/recipe/2020/10/13/0782a3bab6719c355266869f638fd28d1.jpg",
		"https://recipe1.ezmember.co.kr/cache/recipe/2020/10/13/25ab202fdfa68150b68465a4c653885e1.jpg",
		"https://recipe1.ezmember.co.kr/cache/recipe/2020/10/13/0f83e64c29533f59fe125138212144301.jpg",
		"https://recipe1.ezmember.co.kr/cache/recipe/2020/10/13/c1b815738a64d67b3cadd8a693aa65861.jpg",
		"https://recipe1.ezmember.co.kr/cache/recipe/2020/10/13/e7ac61e414f70b02cd1ac3b533e64acf1.jpg",
		"https://recipe1.ezmember.co.kr/cache/recipe/2020/10/13/2160cf969b51959d6155a49bcc6c96631.jpg"
	]
}