{
	"id": "6945733",
	"name": "모과청만들기~달콤하면서도 향이좋아요",
	"thumbnail": "https://recipe1.ezmember.co.kr/cache/recipe/2020/11/05/7b815cd6f07e035b6e6a838195a993651.jpg",
	"url": "https://www.10000recipe.com/recipe/6945733",
	"ingredient_ids": [
		139,
		227,
		226
	],
	"time": "60",
	"ingre_list": [
		{
			"ingre_name": "모과",
			"ingre_count": "1",
			"ingre_unit": "kg"
		},
		{
			"ingre_name": "꿀",
			"ingre_count": "500",
			"ingre_unit": "g"
		},
		{
			"ingre_name": "설탕",
			"ingre_count": "500",
			"ingre_unit": "g"
		},
		{
			"ingre_name": "소독된유리병",
			"ingre_count": "1",
			"ingre_unit": "개"
		}
	],
	"recipe": [
		"1.  @6945732  모과를 세척/손질법으로 쉽게 손질한 모과를 최대한 얇게 슬라이드해주세요 채를 썰어주셔도 되지만 모과를 썰어보시면 좀 힘들어요 그리고 저는 차로 먹으면서 모과가 딸려오는게 싫어서 채를 썰지않고 그냥 얇게 슬라이드해주네요",
		"2. 흰설탕 500g/아카시아꿀500g을 1:1비율로 준비했어요 취향껏 설탕으로 모과의 동량을 넣어주셔도 되시고 꿀을 동량을 넣어주셔도 되세요",
		"3. 슬라이드해준 모과에 꿀을 먼저 넣고 비벼주신후",
		"4. 설탕을 넣고 버려주셔도 되시고  소독된 유리병에 썰어주신 모과를 다넣고 꿀을 넣고 그위에 설탕을 넣어올려주셔도 되시고요  저처럼 빨리 드시고 싶으시면 두개다 섞어서 설탕을 녹여주신후 용기에 담아주셔도 되세요",
		"5. 버무려준 모과를 유리용기에 넣고 뚜껑을 닫아 실온에 2~3일을 보관후에 냉장고에 1~2주를 보관하셨다가 조금씩 덜어내셔서 차로 드셔주시면 되세요 과일청들은 조금씩 바로바로 만들어 드시거나 오래보관 하실경우는 큰용기말고 작은용기에 소분해서 냉장보관해주시면서 드세요"
	],
	"recipe_img": [
		"https://recipe1.ezmember.co.kr/cache/recipe/2020/11/05/694ef8a0bb47f6fbe7f904ef8bb1683b1.jpg",
		"https://recipe1.ezmember.co.kr/cache/recipe/2020/11/05/2588b710ce91fd25ca627323c23198051.jpg",
		"https://recipe1.ezmember.co.kr/cache/recipe/2020/11/05/35f2c29aff15e64979c485c9438dd0c81.jpg",
		"https://recipe1.ezmember.co.kr/cache/recipe/2020/11/05/4c007102bd1e6b72166d7a48394e01321.jpg",
		"https://recipe1.ezmember.co.kr/cache/recipe/2020/11/05/627589865f7e764ecd2e0859557fbbd31.jpg"
	]
}