{
	"id": "748769",
	"name": "남은 잡채의 변신 잡채군만두",
	"thumbnail": "https://recipe1.ezmember.co.kr/cache/recipe/2015/10/02/b64f1e03c35554c165dce12d4a131c18.jpg",
	"url": "https://www.10000recipe.com/recipe/748769",
	"ingredient_ids": [
		1025,
		323,
		286,
		379,
		231
	],
	"time": "30",
	"ingre_list": [
		{
			"ingre_name": "잡채",
			"ingre_count": "1",
			"ingre_unit": "대접"
		},
		{
			"ingre_name": "두부",
			"ingre_count": "1",
			"ingre_unit": "모"
		},
		{
			"ingre_name": "만두피",
			"ingre_count": "40",
			"ingre_unit": "장"
		},
		{
			"ingre_name": "간장",
			"ingre_count": "1",
			"ingre_unit": "큰술"
		},
		{
			"ingre_name": "식초",
			"ingre_count": "1",
			"ingre_unit": "큰술"
		}
	],
	"recipe": [
		"1. 우선 잡채를 가위로 잘라주세용. 만두소로 사용될꺼니까 잘게 잘라주세용.",
		"2. 두부 1모를 물기를 짜서 볼에 담아주세용.",
		"3. 잘라둔 잡채를 두부에 섞어주세용. 재료에 점성이 생기도록 잘 치대주세용. 초간단 만두소 완성. 잡채도 두부에도 간이 되어있으니 따로 간을 해주지 않으셔도 되용.",
		"4. 밥숟가락으로 만두소를 한큰술 떠서 만두피에 얹어주세요.",
		"5. 만두피 가장자리에 따뜻한 물을 발라주세용.",
		"6. 이젠 마음대로 만두 빚기. 전 시판되는 만두랑 비슷하게 빚어보고자 이렇게 했답니당. 만두를 이쁘게 빚어야 예쁜아가야를 낳는단 말씀 아시죵. 열심히 이뿌게 빚어야해용. 아이의 미래를 위해서용.",
		"7. 요렇게 후다닥 만두를 빚었어요. 웬지 좀 어설프죠? 좀 더 이쁜 모양으로 빚고 싶었는데 내공부족으로 이것으로 만족. 전 쟁반에 붓지 않게 하려고 밀가루를 너무 많이 사용했는데 찌지 않고 바로 튀겨서 드시려면 되도록이면 밀가루를 적게 사용할수록 좋아요. 밀가루가 기름을 빨리 변색시키고 텁텁한 맛을 내거든용.",
		"8. 달궈진 팬에 기름을 넉넉하게 붓고 만두를 구워주세용. 반쯤 튀긴듯이 구워주시면 되용.",
		"9. 만두가 구워지는 동안 간단하게 초간장을 만들어 줄꺼에요. 간장 1큰술에 식초 1큰술 그럼 끝이랍니당.",
		"10. 식초가 들어가서 군만두의 기름진 맛을 없애준답니당. 그리고 간장의 짠맛을 중화시켜주기도 하구요. 이미 만두소에 간이 되어있기 때문에 간장이 심심한편이 좋아요.",
		"11. 사방을 돌아가면서 바삭하게 튀겨내주세용. 노릇노릇 맛있게 구워졌죵.",
		"12. 짜잔. 노릇노릇 맛있는 잡채군만두 완성이에요. 정말 후다닥 만들었네용. 먹다 남아 애물단지가 되었던 잡채가 이렇게 먹음직스러운 군만두로 변신을 했답니당. 겉은 바삭바삭하고 속안에 푸짐한 잡채가 가득하답니당.여러분께서도 집에 잡채가 있으시면 이렇게 만들어보셔용. 간식으로 넘넘 좋아요. 간단해서 만드는 엄마도 참 편하구요."
	],
	"recipe_img": [
		"https://recipe1.ezmember.co.kr/cache/recipe/2015/10/05/26133861e3656e90a88c772a7caa76c71.jpg",
		"https://recipe1.ezmember.co.kr/cache/recipe/2015/10/05/cf1f535938bfae6ada19a064b42019e61.jpg",
		"https://recipe1.ezmember.co.kr/cache/recipe/2015/10/05/8578b4a475ec366c38fdef92ab262e6d1.jpg",
		"https://recipe1.ezmember.co.kr/cache/recipe/2015/10/05/fdc135c570558b2065b89ea1ad6041cd1.jpg",
		"https://recipe1.ezmember.co.kr/cache/recipe/2015/10/05/2c36d10dc40ca3ecd849260211adee1d1.jpg",
		"https://recipe1.ezmember.co.kr/cache/recipe/2015/10/05/c98d165bda59d6c84e3d2bd47d420f6e1.jpg",
		"https://recipe1.ezmember.co.kr/cache/recipe/2015/10/05/afdf23e4b94610dd4ac1bc02d2d546131.jpg",
		"https://recipe1.ezmember.co.kr/cache/recipe/2015/10/05/996faf23f1c2dd270a9fa2d1bf4dfee11.jpg",
		"https://recipe1.ezmember.co.kr/cache/recipe/2015/10/05/aca8de0e1224e26bf29097fc7a43c24d1.jpg",
		"https://recipe1.ezmember.co.kr/cache/recipe/2015/10/05/fe677a85208f46662191f6fdbec2a1ba1.jpg",
		"https://recipe1.ezmember.co.kr/cache/recipe/2015/10/05/476b05afcd1c6c08884419eb2f325f0f1.jpg",
		"https://recipe1.ezmember.co.kr/cache/recipe/2015/10/05/01c787808e0217cdf9a86fb57caf87ff1.jpg"
	]
}